duffy/__init__.py
duffy/admin.py
duffy/api_models/__init__.py
duffy/api_models/common.py
duffy/api_models/node.py
duffy/api_models/pool.py
duffy/api_models/session.py
duffy/api_models/tenant.py
duffy/app/__init__.py
duffy/app/auth.py
duffy/app/controllers/__init__.py
duffy/app/controllers/node.py
duffy/app/controllers/pool.py
duffy/app/controllers/session.py
duffy/app/controllers/tenant.py
duffy/app/database.py
duffy/app/logging.py
duffy/app/main.py
duffy/app/middleware.py
duffy/app/util.py
duffy/cli.py
duffy/client/__init__.py
duffy/client/formatter.py
duffy/client/main.py
duffy/configuration/__init__.py
duffy/configuration/main.py
duffy/configuration/validation.py
duffy/database/__init__.py
duffy/database/migrations/env.py
duffy/database/migrations/main.py
duffy/database/migrations/script.py.mako
duffy/database/migrations/versions/.empty
duffy/database/migrations/versions/36cf064c0481_ignore_failed_nodes_in_unique_indexes.py
duffy/database/migrations/versions/6654d536b836_add_node_state_sessionnode_session_id_.py
duffy/database/migrations/versions/ce2e575cb800_add_tenant_session_lifetimes.py
duffy/database/model/__init__.py
duffy/database/model/node.py
duffy/database/model/session.py
duffy/database/model/tenant.py
duffy/database/setup.py
duffy/database/types.py
duffy/database/util.py
duffy/exceptions.py
duffy/legacy/__init__.py
duffy/legacy/api_models.py
duffy/legacy/auth.py
duffy/legacy/main.py
duffy/misc.py
duffy/nodes/__init__.py
duffy/nodes/context.py
duffy/nodes/mechanisms/__init__.py
duffy/nodes/mechanisms/ansible.py
duffy/nodes/mechanisms/main.py
duffy/nodes/pools.py
duffy/shell.py
duffy/tasks/__init__.py
duffy/tasks/base.py
duffy/tasks/deprovision.py
duffy/tasks/expire.py
duffy/tasks/locking.py
duffy/tasks/main.py
duffy/tasks/provision.py
duffy/util.py
duffy/version.py
duffy-3.4.0.dist-info/LICENSE
duffy-3.4.0.dist-info/METADATA
duffy-3.4.0.dist-info/WHEEL
duffy-3.4.0.dist-info/entry_points.txt
duffy-3.4.0.dist-info/RECORD
