Metadata-Version: 2.1
Name: duffy
Version: 3.4.0
Summary: CentOS CI provisioner
Home-page: https://github.com/CentOS/duffy
License: MIT
Keywords: baremetal,ci,vm,opennebula,centos
Author: Nils Philippsen
Author-email: nils@redhat.com
Maintainer: Nils Philippsen
Maintainer-email: nils@redhat.com
Requires-Python: >=3.8,<4.0
Classifier: Development Status :: 4 - Beta
Classifier: Environment :: Web Environment
Classifier: Framework :: Ansible
Classifier: Framework :: AsyncIO
Classifier: Framework :: Celery
Classifier: Framework :: FastAPI
Classifier: Intended Audience :: System Administrators
Classifier: License :: OSI Approved :: MIT License
Classifier: Natural Language :: English
Classifier: Operating System :: POSIX :: Linux
Classifier: Programming Language :: Python :: 3
Classifier: Programming Language :: Python :: 3.8
Classifier: Programming Language :: Python :: 3.9
Classifier: Programming Language :: Python :: 3.10
Classifier: Programming Language :: Python :: 3.11
Classifier: Programming Language :: Python :: 3.12
Classifier: Programming Language :: Python :: 3.13
Classifier: Topic :: Internet :: WWW/HTTP :: WSGI :: Application
Classifier: Topic :: Software Development :: Build Tools
Classifier: Topic :: Software Development :: Quality Assurance
Classifier: Topic :: Software Development :: Testing
Classifier: Topic :: System :: Monitoring
Classifier: Topic :: System :: Operating System
Provides-Extra: admin
Provides-Extra: app
Provides-Extra: client
Provides-Extra: database
Provides-Extra: dev-shell
Provides-Extra: legacy
Provides-Extra: postgresql
Provides-Extra: sqlite
Provides-Extra: tasks
Requires-Dist: Jinja2 (>=3.0.3,<4.0.0) ; extra == "app" or extra == "tasks" or extra == "legacy"
Requires-Dist: PyYAML (>=6,<7)
Requires-Dist: SQLAlchemy[asyncio] (>=2.0.5,<3.0.0) ; extra == "app" or extra == "admin" or extra == "database" or extra == "dev-shell"
Requires-Dist: aiodns (>=3.0.0,<4.0.0) ; extra == "app" or extra == "tasks"
Requires-Dist: aiosqlite (>=0.17,<0.22.0) ; extra == "sqlite"
Requires-Dist: alembic (>=1.7.5,<2.0.0) ; extra == "app" or extra == "database" or extra == "dev-shell"
Requires-Dist: ansible-runner (>=2.1.1,<2.4) ; (python_version >= "3.8" and python_version < "3.9") and (extra == "app" or extra == "tasks")
Requires-Dist: ansible-runner (>=2.4,<3.0) ; (python_version >= "3.9" and python_version < "4") and (extra == "app" or extra == "tasks")
Requires-Dist: asyncpg (>=0.25,<0.31.0) ; extra == "postgresql"
Requires-Dist: bcrypt (>=3.2,<5) ; extra == "app" or extra == "admin" or extra == "database" or extra == "dev-shell"
Requires-Dist: celery[redis] (>=5.2.1,<6.0.0) ; extra == "app" or extra == "tasks"
Requires-Dist: click (>=8.0.3,<9.0.0)
Requires-Dist: fastapi (>=0.93,<0.116.0) ; extra == "app" or extra == "admin"
Requires-Dist: greenlet (>=2,<4)
Requires-Dist: httpx (>=0.18.2,<0.29.0) ; extra == "legacy" or extra == "client"
Requires-Dist: ipython (>=7.29,<10.0.0) ; extra == "dev-shell"
Requires-Dist: jmespath (>=0.10,<2) ; extra == "app" or extra == "tasks"
Requires-Dist: pottery (>=3,<4) ; extra == "app" or extra == "tasks"
Requires-Dist: psycopg2 (>=2.9.2,<3.0.0) ; extra == "postgresql"
Requires-Dist: pydantic (>=2.0.3,<3.0.0)
Requires-Dist: pyxdg (>=0.27,<0.29)
Requires-Dist: typing-extensions (>=4.6.1,<5.0.0)
Requires-Dist: uvicorn (>=0.15,<0.35.0) ; extra == "app"
Project-URL: Documentation, https://github.com/CentOS/duffy/wiki
Project-URL: Repository, https://github.com/CentOS/duffy
